client.py
server.py
thecrypt-1.0.2.dist-info/entry_points.txt
thecrypt-1.0.2.dist-info/WHEEL
thecrypt-1.0.2.dist-info/METADATA
thecrypt-1.0.2.dist-info/RECORD
