Metadata-Version: 2.1
Name: thecrypt
Version: 1.0.2
Summary: A peer-to-peer encrypted command line chatroom.
License: MIT
Author: CarterFaceySmith
Author-email: carterfaceysmith@gmail.com
Requires-Python: >=3.8,<4.0
Classifier: License :: OSI Approved :: MIT License
Classifier: Programming Language :: Python :: 3
Classifier: Programming Language :: Python :: 3.8
Classifier: Programming Language :: Python :: 3.9
Classifier: Programming Language :: Python :: 3.10
Requires-Dist: cryptography (>=38.0.1,<39.0.0)
